{"id":"6F611CC1-3F21-4D06-989A-48574F14DD8E","dataPathRelativeToProjectURL":"..\/..\/..\/..\/Downloads\/BetterRest.csv\/","version":"1.0","createdDate":"2024-02-20T14:11:05Z","dataURL":"file:\/\/\/Users\/jacksonharrison\/Downloads\/BetterRest.csv","dataResult":{"dataURL":"file:\/\/\/Users\/jacksonharrison\/Downloads\/BetterRest.csv","createdDate":"2024-02-20T14:11:05Z","dataSourceID":"6F611CC1-3F21-4D06-989A-48574F14DD8E"},"activityEntities":["dataSourceTrainingStarted",[{"id":"0E9C6B68-CFE8-405B-884D-3A4158E84830","title":"Used By","createdDate":"2024-02-20T14:14:25Z","event":"dataSourceTrainingStarted","subtitle":"BetterRest 1"}],"dataSourceMetrics",[{"id":"260AC4CC-75E1-4924-8EB9-B2E5DA79872D","title":"Data Summary","createdDate":"2024-02-20T14:14:25Z","event":"dataSourceMetrics","subtitle":"10,000 Items"}]],"title":"BetterRest.csv","pathType":0,"modifiedDate":"2024-02-20T14:14:25Z","preferredFilename":"BetterRest.csv","experimentIDs":["B0BE0088-8C54-4D00-A33B-4451B5489DDD"]}